jupyter_background_keepalive/__init__.py
jupyter_background_keepalive/background_keepalive.py
jupyter_background_keepalive/py.typed
jupyter_background_keepalive-0.1.6.dist-info/WHEEL
jupyter_background_keepalive-0.1.6.dist-info/METADATA
jupyter_background_keepalive-0.1.6.dist-info/RECORD
