Metadata-Version: 2.3
Name: jupyter-background-keepalive
Version: 0.1.6
Summary: Initialize a background thread that pings Jupyter so that it doesn't get culled
Author: Muhammad Alif Putra Yasa
Author-email: Muhammad Alif Putra Yasa <130131893+alifyasa@users.noreply.github.com>
Requires-Dist: requests>=2.27.1
Requires-Python: >=3.6
